{
	"agcgw_all":{
		"CN":"connect-drcn.dbankcloud.cn",
		"CN_back":"connect-drcn.hispace.hicloud.com",
		"DE":"connect-dre.dbankcloud.cn",
		"DE_back":"connect-dre.hispace.hicloud.com",
		"RU":"connect-drru.hispace.dbankcloud.ru",
		"RU_back":"connect-drru.hispace.dbankcloud.ru",
		"SG":"connect-dra.dbankcloud.cn",
		"SG_back":"connect-dra.hispace.hicloud.com"
	},
	"client":{
		"cp_id":"2640062000021338168",
		"product_id":"99536292102069515",
		"client_id":"845034774350286208",
		"client_secret":"C8288B24FEAABAEB530E2C4EEFF7C55D177B8B2A1B175EF86FC14194F86F8CB0",
		"project_id":"99536292102069515",
		"app_id":"105747573",
		"api_key":"DAEDAEOYZZEMIERp6XdvEO7NRbbE1GBDJmer5PTGx74NGheook2Ko9hdNA6A3BvN7BLU/mspExBEendeGe9CMymu2YR79IjfeuEuXA==",
		"package_name":"itts.dicky.surachman.task2"
	},
	"oauth_client":{
		"client_id":"105747573",
		"client_type":1
	},
	"app_info":{
		"app_id":"105747573",
		"package_name":"itts.dicky.surachman.task2"
	},
	"configuration_version":"3.0",
	"appInfos":[
		{
			"package_name":"itts.dicky.surachman.task2",
			"client":{
				"app_id":"105747573"
			},
			"app_info":{
				"package_name":"itts.dicky.surachman.task2",
				"app_id":"105747573"
			},
			"oauth_client":{
				"client_type":1,
				"client_id":"105747573"
			}
		}
	]
}